zg_crawl_tools/__init__.py
zg_crawl_tools/bloomfilter_module/__init__.py
zg_crawl_tools/bloomfilter_module/bloom_check.py
zg_crawl_tools/cipher_moudle/__init__.py
zg_crawl_tools/cipher_moudle/cipher_calculate.py
zg_crawl_tools/requests_moudle/__init__.py
zg_crawl_tools/requests_moudle/zg_extract_response.py
zg_crawl_tools/requests_moudle/zg_request.py
zg_crawl_tools-0.0.2.dist-info/LICENSE
zg_crawl_tools-0.0.2.dist-info/METADATA
zg_crawl_tools-0.0.2.dist-info/WHEEL
zg_crawl_tools-0.0.2.dist-info/top_level.txt
zg_crawl_tools-0.0.2.dist-info/RECORD
