Metadata-Version: 2.1
Name: zg_crawl_tools
Version: 0.0.2
Summary: A small example package
Author-email: by_yuanyuan <zhiboyuan666@gmail.com>
Classifier: Programming Language :: Python :: 3
Classifier: License :: OSI Approved :: MIT License
Classifier: Operating System :: OS Independent
Requires-Python: >=3.8
License-File: LICENSE
Requires-Dist: requests
Requires-Dist: lxml
Requires-Dist: redisbloom
Requires-Dist: pycryptodome
